{
  "fitnessActivity": "walking",
  "startTime": "2022-07-13T12:09:37.701Z",
  "endTime": "2022-07-13T12:54:38.428Z",
  "duration": "2143.029s",
  "segment": [{
    "fitnessActivity": "walking",
    "startTime": "2022-07-13T12:09:37.701Z",
    "endTime": "2022-07-13T12:11:36.244Z"
  }, {
    "fitnessActivity": "walking",
    "startTime": "2022-07-13T12:11:36.244Z",
    "endTime": "2022-07-13T12:18:57.317Z"
  }, {
    "fitnessActivity": "walking",
    "startTime": "2022-07-13T12:28:15.015Z",
    "endTime": "2022-07-13T12:54:38.428Z"
  }],
  "aggregate": [{
    "metricName": "com.google.heart_minutes.summary",
    "floatValue": 5.0
  }, {
    "metricName": "com.google.calories.expended",
    "floatValue": 168.3719773152469
  }, {
    "metricName": "com.google.step_count.delta",
    "intValue": 2107
  }, {
    "metricName": "com.google.distance.delta",
    "floatValue": 1397.2768358926214
  }, {
    "metricName": "com.google.speed.summary",
    "floatValue": 0.8571328775269762
  }, {
    "metricName": "com.google.active_minutes",
    "intValue": 29
  }]
}